naga_helper/__init__.py
naga_helper/analyzer.py
naga_helper/analyzer_test.py
naga_helper/utils.py
naga_helper/plugins/__init__.py
naga_helper/plugins/naga_webpage.py
naga_helper-0.2.17.dist-info/licenses/LICENSE
naga_helper-0.2.17.dist-info/METADATA
naga_helper-0.2.17.dist-info/WHEEL
naga_helper-0.2.17.dist-info/top_level.txt
naga_helper-0.2.17.dist-info/RECORD
