Metadata-Version: 2.4
Name: naga_helper
Version: 0.2.17
Summary: Analyze reports of riichi mahjong AI NAGA and Mortal.
Author-email: Jianing Shi <1176827825@qq.com>
License: GNU Affero General Public License v3
Project-URL: Homepage, https://github.com/sjn4048/naga_helper
Project-URL: Source, https://github.com/sjn4048/naga_helper
Keywords: mahjong,riichi,naga,mortal,majsoul,tenhou,ai
Classifier: Programming Language :: Python :: 3
Classifier: License :: OSI Approved :: GNU Affero General Public License v3
Classifier: Operating System :: OS Independent
Requires-Python: >=3.6
License-File: LICENSE
Requires-Dist: demjson3>=3.0.5
Requires-Dist: numpy<2.0.0,>=1.26.4
Requires-Dist: requests<3.0.0,>=2.32.0
Requires-Dist: beautifulsoup4>=4.11.1
Requires-Dist: mahjong<2.0.0,>=1.2.1
Requires-Dist: tqdm>=4.0.0
Dynamic: license-file
